sfunc/__init__.py
sfunc/apigw_request.py
sfunc/apigw_response.py
tests/__init__.py
tests/apigw_request_test.py
tests/apigw_response_test.py
tests/sfunc_test.py
sfunc-0.3.2.dist-info/METADATA
sfunc-0.3.2.dist-info/WHEEL
sfunc-0.3.2.dist-info/top_level.txt
sfunc-0.3.2.dist-info/RECORD
