Metadata-Version: 2.1
Name: sfunc
Version: 0.3.2
Summary: Wrappers for using a single lambda function for AWS ApiGateway
Home-page: https://github.com/hawry/sfunc
Author: hawry
License: UNKNOWN
Platform: UNKNOWN
Requires-Python: >=3.6
